graspologic/__init__.py
graspologic/align/__init__.py
graspologic/align/base.py
graspologic/align/orthogonal_procrustes.py
graspologic/align/seedless_procrustes.py
graspologic/align/sign_flips.py
graspologic/cluster/__init__.py
graspologic/cluster/autogmm.py
graspologic/cluster/base.py
graspologic/cluster/divisive_cluster.py
graspologic/cluster/gclust.py
graspologic/cluster/kclust.py
graspologic/datasets/__init__.py
graspologic/datasets/base.py
graspologic/datasets/drosophila/left_adjacency.csv
graspologic/datasets/drosophila/left_cell_labels.csv
graspologic/datasets/drosophila/right_adjacency.csv
graspologic/datasets/drosophila/right_cell_labels.csv
graspologic/datasets/mice/atlas.csv
graspologic/datasets/mice/blocks.csv
graspologic/datasets/mice/edgelists/sub-54776_ses-1_dti.edgelist
graspologic/datasets/mice/edgelists/sub-54777_ses-1_dti.edgelist
graspologic/datasets/mice/edgelists/sub-54779_ses-1_dti.edgelist
graspologic/datasets/mice/edgelists/sub-54781_ses-1_dti.edgelist
graspologic/datasets/mice/edgelists/sub-54790_ses-1_dti.edgelist
graspologic/datasets/mice/edgelists/sub-54793_ses-1_dti.edgelist
graspologic/datasets/mice/edgelists/sub-54794_ses-1_dti.edgelist
graspologic/datasets/mice/edgelists/sub-54797_ses-1_dti.edgelist
graspologic/datasets/mice/edgelists/sub-54811_ses-1_dti.edgelist
graspologic/datasets/mice/edgelists/sub-54813_ses-1_dti.edgelist
graspologic/datasets/mice/edgelists/sub-54815_ses-1_dti.edgelist
graspologic/datasets/mice/edgelists/sub-54817_ses-1_dti.edgelist
graspologic/datasets/mice/edgelists/sub-54821_ses-1_dti.edgelist
graspologic/datasets/mice/edgelists/sub-54823_ses-1_dti.edgelist
graspologic/datasets/mice/edgelists/sub-54829_ses-1_dti.edgelist
graspologic/datasets/mice/edgelists/sub-54831_ses-1_dti.edgelist
graspologic/datasets/mice/edgelists/sub-54833_ses-1_dti.edgelist
graspologic/datasets/mice/edgelists/sub-54835_ses-1_dti.edgelist
graspologic/datasets/mice/edgelists/sub-54842_ses-1_dti.edgelist
graspologic-3.4.4.dist-info/LICENSE.txt
graspologic-3.4.4.dist-info/METADATA
graspologic-3.4.4.dist-info/WHEEL
graspologic-3.4.4.dist-info/RECORD
